pypkgs_khanhvu/__init__.py
pypkgs_khanhvu/pypkgs_khanhvu.py
pypkgs_khanhvu-0.1.0.dist-info/LICENSE
pypkgs_khanhvu-0.1.0.dist-info/WHEEL
pypkgs_khanhvu-0.1.0.dist-info/METADATA
pypkgs_khanhvu-0.1.0.dist-info/RECORD
