Metadata-Version: 2.1
Name: pypkgs-khanhvu
Version: 0.1.0
Summary: Individual Assignment 1 for 524
License: MIT
Author: Tran Doan Khanh Vu
Author-email: tdkhanhvu@gmail.com
Requires-Python: >=3.8,<4.0
Classifier: License :: OSI Approved :: MIT License
Classifier: Programming Language :: Python :: 3
Classifier: Programming Language :: Python :: 3.8
Classifier: Programming Language :: Python :: 3.9
Requires-Dist: pandas (>=1.2.2,<2.0.0)
